shup/__init__.py
shup/config.py
shup/error.py
shup/shup.cfg
shup/shup.py
shup-0.2.0.dist-info/DESCRIPTION.rst
shup-0.2.0.dist-info/METADATA
shup-0.2.0.dist-info/RECORD
shup-0.2.0.dist-info/WHEEL
shup-0.2.0.dist-info/entry_points.txt
shup-0.2.0.dist-info/metadata.json
shup-0.2.0.dist-info/top_level.txt
