Metadata-Version: 2.0
Name: shup
Version: 0.2.0
Summary: File sharing (images, code snippets, movies...) made easy.
Home-page: https://github.com/Naam/shup
Author: Nahim El Atmani
Author-email: nahim+dev@naam.me
License: GPL3
Keywords: upload sharing share file tool upload snippet code image
Platform: UNKNOWN
Classifier: Development Status :: 4 - Beta
Classifier: Intended Audience :: System Administrators
Classifier: Intended Audience :: Information Technology
Classifier: Natural Language :: English
Classifier: Operating System :: OS Independent
Classifier: Programming Language :: Python :: 3
Classifier: License :: OSI Approved :: GNU General Public License v3 (GPLv3)
Classifier: Topic :: System :: Archiving
Classifier: Topic :: Communications :: File Sharing
Classifier: Programming Language :: Python :: 3
Classifier: Programming Language :: Python :: 3.2
Classifier: Programming Language :: Python :: 3.3
Classifier: Programming Language :: Python :: 3.4
Classifier: Programming Language :: Python :: 3.5
Classifier: Programming Language :: Python :: 3.6
Classifier: Programming Language :: Python :: 3.7
Provides: shup
Requires-Python: >=3
Requires-Dist: paramiko (>=1.16.0)
Requires-Dist: progressbar2 (>=3.34.3)
